shopcloud_django_toolbox/__init__.py
shopcloud_django_toolbox/admin.py
shopcloud_django_toolbox/decorators.py
shopcloud_django_toolbox/events.py
shopcloud_django_toolbox/hash_for_file.py
shopcloud_django_toolbox/models.py
shopcloud_django_toolbox/renders.py
shopcloud_django_toolbox/signer.py
shopcloud_django_toolbox/tests.py
shopcloud_django_toolbox/urltools.py
shopcloud_django_toolbox/views.py
shopcloud_django_toolbox-1.20.0.dist-info/licenses/LICENSE
shopcloud_django_toolbox-1.20.0.dist-info/METADATA
shopcloud_django_toolbox-1.20.0.dist-info/WHEEL
shopcloud_django_toolbox-1.20.0.dist-info/top_level.txt
shopcloud_django_toolbox-1.20.0.dist-info/RECORD
