Metadata-Version: 2.4
Name: shopcloud_django_toolbox
Version: 1.20.0
Summary: Django tool
Home-page: https://github.com/Talk-Point/shopcloud-django-toolbox
Author: Konstantin Stoldt
Author-email: konstantin.stoldt@talk-point.de
License: MIT
License-File: LICENSE
Requires-Dist: Django<7.0,>=3.2
Requires-Dist: djangorestframework
Dynamic: author
Dynamic: author-email
Dynamic: description
Dynamic: description-content-type
Dynamic: home-page
Dynamic: license
Dynamic: license-file
Dynamic: requires-dist
Dynamic: summary
